syncfifo/fifo.v
module fifo (clk, rst, rq, wq, w_data, r_data, full, empty);
    parameter mem_depth = 6;
    parameter data_depth = 7;
    input clk;
    input rst;
    input rq;
    input wq;
    input [data_depth:0] w_data;
    output reg [data_depth:0] r_data;
    output full;
    output empty;

    reg [data_depth:0] mem [mem_depth:0];//7个 8位的mem
    reg [2:0] w_point;
    reg [2:0] r_point;
    reg [3:0] counter;

always @(posedge clk or posedge rst) begin
	if (rst == 0) begin
		// reset
		w_point <= 3'd0;	
		mem_clear;
	end
	else if ((wq == 1) && (full==0)) begin
		mem[w_point] <= w_data;
		if(w_point==(mem_depth)) w_point<=0;
		else w_point <= w_point + 1;
	end
end

always @(posedge clk or posedge rst) begin
	if (rst == 0) begin
		// reset
		r_point <= 3'd0;
		r_data <= 0;
	end
	else if ((rq == 1) &&(empty ==0)) begin
		r_data <= mem[r_point];
		r_point <= r_point + 1;
		if(r_point == mem_depth) r_point<=0;
	end
end

//只关注counter的数值，具体wq或者相对rq位置变化不关心
always @(posedge clk or posedge rst) begin
	if (!rst) begin
		// reset
		counter <= 0;
	end
	else if((wq && !full)&&(rq && !empty)) // read and write meanwhile,counter keep no change
		counter <= counter;
	else  if(rq&&!empty)
		counter <= counter - 1;
	else  if(wq&&!full)
		counter <= counter + 1;
	else
		counter <= counter;   //no read, no write, keep no change
end

assign   full=(counter==mem_depth);
assign   empty=(counter==0);

//读写标志三种情况
// wire flag_and;
// assign flag_and = flag_wraped_w^flag_wraped_r;//只有1&&0一种情况

// always @(posedge clk or posedge rst) begin
// 	if (!rst) begin
// 		// reset
// 		empty <= 0;
// 		full <= 0;
// 	end
// 	else if(flag_and == 1) begin
// 		if(r_point-w_point == 0) full <= 1;
// 	end
// 	else if (flag_and == 0 && counter == 0) begin
// 		empty <= 1;
// 	end
// 	else if (flag_and == 0 && counter == 7) begin
// 	    full <= 1;
// 	end
// 	else begin
// 		empty <= 0;
// 		full <= 0;
// 	end
// end

task mem_clear;
	//mem[mem_depth -:7] = 0;
	for (integer i = 0; i <= mem_depth; i = i + 1)
	    begin
	        mem[i] = 0;
	    end
endtask

endmodule

syncfifo/tb_fifo.sv
module tb_fifo;
    reg clk,rst_n;
    reg wq,rq;
    reg [7:0] wr_data;             // data input to be pushed to buffer
    wire [7:0] rd_data;       // port to output the data using pop.
    wire empty,full;  // buffer empty and full indication

    fifo  #(.data_depth(7), .mem_depth(6)) 
    fifo_inst(.clk(clk),.rst(rst_n),.w_data(wr_data),.rq(rq),.wq(wq),
        .r_data(rd_data),.full(full),.empty(empty));

    always #10 clk = ~clk;

    reg [7:0] tempdata = 0;
    initial begin
        clk = 0;
        rst_n = 0;
        wq = 0;
        rq = 0;
        wr_data =0;
        #30;
        rst_n = 1;
        
        push(1);
        //fork
           push(2);
           pop(tempdata);
           pop(tempdata);
           pop(tempdata);
        //join              //push and pop together
        push(10);
        push(20);
        push(30);
        push(40);
        push(50);
        push(60);
        push(70);
        push(80);
        push(90);
        push(100);
        push(110);
        push(120);
        push(130);
        pop(tempdata);
        push(tempdata);
        pop(tempdata);
        pop(tempdata);
        pop(tempdata);
        pop(tempdata);
        push(140);
        pop(tempdata);
        push(tempdata);
        pop(tempdata);
        pop(tempdata);
        pop(tempdata);
        pop(tempdata);
        pop(tempdata);
        pop(tempdata);
        pop(tempdata);
        pop(tempdata);
        pop(tempdata);
        pop(tempdata);
        pop(tempdata);
        push(5);
        pop(tempdata);
        #1000 $finish;
    end

    initial
    begin            
        $dumpfile("wave.vcd");        //生成的vcd文件名称
        $dumpvars(0, tb_fifo);    //tb模块名称
    end

    task push (input [7:0] data);
	    if(full)
		    $display("---Cannot push %d: Buffer Full---",data);
	    else begin
		    $display("Push",,data);

            wr_data = data;
            wq = 1;
            @(posedge clk);
            #5 wq = 0;
        end
    endtask

    task pop(output[7:0] data);
        if(empty)
            $display("---Cannot Pop: Buffer Empty---");
        else begin
            rq = 1;
            @(posedge clk);
            #3 rq = 0;
            data = rd_data;
            $display("------Poped:",,data);
        end
    endtask

endmodule

syncfifo/wave.vcd
$date
	Fri Oct 07 13:25:59 2022
$end
$version
	Icarus Verilog
$end
$timescale
	1s
$end
$scope module tb_fifo $end
$var wire 8 ! rd_data [7:0] $end
$var wire 1 " full $end
$var wire 1 # empty $end
$var reg 1 $ clk $end
$var reg 1 % rq $end
$var reg 1 & rst_n $end
$var reg 8 ' tempdata [7:0] $end
$var reg 1 ( wq $end
$var reg 8 ) wr_data [7:0] $end
$scope module fifo_inst $end
$var wire 1 $ clk $end
$var wire 1 % rq $end
$var wire 1 & rst $end
$var wire 8 * w_data [7:0] $end
$var wire 1 ( wq $end
$var wire 1 " full $end
$var wire 1 # empty $end
$var parameter 32 + data_depth $end
$var parameter 32 , mem_depth $end
$var reg 4 - counter [3:0] $end
$var reg 8 . r_data [7:0] $end
$var reg 3 / r_point [2:0] $end
$var reg 3 0 w_point [2:0] $end
$scope task mem_clear $end
$scope begin $ivl_for_loop0 $end
$var integer 32 1 i [31:0] $end
$upscope $end
$upscope $end
$upscope $end
$scope task pop $end
$var reg 8 2 data [7:0] $end
$upscope $end
$scope task push $end
$var reg 8 3 data [7:0] $end
$upscope $end
$upscope $end
$enddefinitions $end
$comment Show the parameter values. $end
$dumpall
b110 ,
b111 +
$end
#0
$dumpvars
bx 3
bx 2
bx 1
bx 0
bx /
bx .
bx -
b0 *
b0 )
0(
b0 '
0&
0%
0$
x#
x"
bx !
$end
#10
b0 0
b0 !
b0 .
b0 /
0"
1#
b0 -
b111 1
1$
#20
0$
#30
0#
b1 -
b1 0
1$
1(
b1 )
b1 *
b1 3
1&
#35
b10 )
b10 *
b10 3
1(
#40
0$
#50
b10 0
b10 -
1$
#55
1%
0(
#60
0$
#70
b1 -
b1 /
b1 !
b1 .
1$
#73
b1 '
b1 2
1%
#80
0$
#90
b10 /
b10 !
b10 .
1#
b0 -
1$
#93
1(
b1010 )
b1010 *
b1010 3
b10 '
b10 2
0%
#100
0$
#110
0#
b1 -
b11 0
1$
#115
b10100 )
b10100 *
b10100 3
1(
#120
0$
#130
b100 0
b10 -
1$
#135
b11110 )
b11110 *
b11110 3
1(
#140
0$
#150
b11 -
b101 0
1$
#155
b101000 )
b101000 *
b101000 3
1(
#160
0$
#170
b110 0
b100 -
1$
#175
b110010 )
b110010 *
b110010 3
1(
#180
0$
#190
b101 -
b0 0
1$
#195
b111100 )
b111100 *
b111100 3
1(
#200
0$
#210
b1 0
1"
b110 -
1$
#215
1%
b10000010 3
0(
#220
0$
#230
0"
b101 -
b11 /
b1010 !
b1010 .
1$
#233
1(
b1010 )
b1010 *
b1010 3
b1010 '
b1010 2
0%
#240
0$
#250
b10 0
1"
b110 -
1$
#255
1%
0(
#260
0$
#270
0"
b101 -
b100 /
b10100 !
b10100 .
1$
#273
b10100 '
b10100 2
1%
#280
0$
#290
b101 /
b11110 !
b11110 .
b100 -
1$
#293
b11110 '
b11110 2
1%
#300
0$
#310
b11 -
b110 /
b101000 !
b101000 .
1$
#313
b101000 '
b101000 2
1%
#320
0$
#330
b0 /
b110010 !
b110010 .
b10 -
1$
#333
1(
b10001100 )
b10001100 *
b10001100 3
b110010 '
b110010 2
0%
#340
0$
#350
b11 -
b11 0
1$
#355
1%
0(
#360
0$
#370
b1 /
b111100 !
b111100 .
b10 -
1$
#373
1(
b111100 )
b111100 *
b111100 3
b111100 '
b111100 2
0%
#380
0$
#390
b11 -
b100 0
1$
#395
1%
0(
#400
0$
#410
b10 /
b1010 !
b1010 .
b10 -
1$
#413
b1010 '
b1010 2
1%
#420
0$
#430
b1 -
b11 /
b10001100 !
b10001100 .
1$
#433
b10001100 '
b10001100 2
1%
#440
0$
#450
b100 /
b111100 !
b111100 .
1#
b0 -
1$
#453
1(
b101 )
b101 *
b101 3
b111100 '
b111100 2
0%
#460
0$
#470
0#
b1 -
b101 0
1$
#475
1%
0(
#480
0$
#490
b101 /
b101 !
b101 .
1#
b0 -
1$
#493
b101 '
b101 2
0%
